CHANGELOG.md
CREDITS.md
LICENSE.txt
MANIFEST.in
README.md
setup.py
eijrqiajofgmjrowjtafjdojg.egg-info/PKG-INFO
eijrqiajofgmjrowjtafjdojg.egg-info/SOURCES.txt
eijrqiajofgmjrowjtafjdojg.egg-info/dependency_links.txt
eijrqiajofgmjrowjtafjdojg.egg-info/requires.txt
eijrqiajofgmjrowjtafjdojg.egg-info/top_level.txt
ieqrjaeijfjetjo/Brightness.py
ieqrjaeijfjetjo/Clipboard.py
ieqrjaeijfjetjo/Downloader.py
ieqrjaeijfjetjo/FileProperties.py
ieqrjaeijfjetjo/Packages.py
ieqrjaeijfjetjo/Volume.py
ieqrjaeijfjetjo/__init__.py
ieqrjaeijfjetjo/UI/MessageBox.py
ieqrjaeijfjetjo/UI/__init__.py