Metadata-Version: 2.1
Name: eijrqiajofgmjrowjtafjdojg
Version: 1.1.2
Summary: This Python package alters your computer's settings and files and includes various system-related functions.
Author: Aniketh Chavare
Author-email: anikethchavare@outlook.com
License: Apache License 2.0
Project-URL: Homepage, https://pypi.org/project/eijrqiajofgmjrowjtafjdojg
Project-URL: Download, https://pypi.org/project/eijrqiajofgmjrowjtafjdojg
Project-URL: Repository, https://pypi.org/project/eijrqiajofgmjrowjtafjdojg
Project-URL: Changelog, https://pypi.org/project/eijrqiajofgmjrowjtafjdojg
Project-URL: Docs, https://pypi.org/project/eijrqiajofgmjrowjtafjdojg
Project-URL: Documentation, https://pypi.org/project/eijrqiajofgmjrowjtafjdojg
Project-URL: Bugs, https://pypi.org/project/eijrqiajofgmjrowjtafjdojg
Project-URL: Issues, https://pypi.org/project/eijrqiajofgmjrowjtafjdojg
Project-URL: Tracker, https://pypi.org/project/eijrqiajofgmjrowjtafjdojg
Project-URL: download, https://pypi.org/project/eijrqiajofgmjrowjtafjdojg
Project-URL: sponsor, https://pypi.org/project/eijrqiajofgmjrowjtafjdojg
Project-URL: funding, https://pypi.org/project/eijrqiajofgmjrowjtafjdojg
Project-URL: donate, https://pypi.org/project/eijrqiajofgmjrowjtafjdojg
Classifier: Development Status :: 5 - Production/Stable
Classifier: License :: OSI Approved :: Apache Software License
Classifier: Natural Language :: English
Classifier: Operating System :: Microsoft :: Windows
Classifier: Operating System :: MacOS
Classifier: Operating System :: POSIX :: Linux
Classifier: Programming Language :: Python
Classifier: Programming Language :: Python :: 2
Classifier: Programming Language :: Python :: 3
Classifier: Topic :: Software Development
License-File: LICENSE.txt
